[
    {
        "contact_id": "67f54d4950de487506065b7f",
        "phone": "551991985536",
        "name": "BRUNA DE AZEVEDO",
        "boleto_url": "https://api.1pay.it/api/boleto/display/3aecd518-fe21-48e8-9b6a-38fcc080ec3d",
        "due_date": "2025-04-22T03:00:00.000Z"
    },
    {
        "contact_id": "680798c8e47c65cd6b0a0dba",
        "phone": "553588217269",
        "name": "ALESSANDRA DE FATIMA SANTOS GARCIA SILVA",
        "boleto_url": "https://api.1pay.it/api/boleto/display/e23aa0c5-fa93-4faa-8861-fd6ea9e9904b",
        "due_date": "2025-04-22T03:00:00.000Z"
    },
    {
        "contact_id": "67d18b7e90dcc988a200bff4",
        "phone": "553597559293",
        "name": "VIVIANE SILVA DE  FARIAS",
        "boleto_url": "https://api.1pay.it/api/boleto/display/e745f93b-ad98-4692-abd5-737ca5e58093",
        "due_date": "2025-04-23T03:00:00.000Z"
    },
    {
        "contact_id": "680a45b232eb0f7e34029e0f",
        "phone": "553598600489",
        "name": "RHENAN FERREIRA DOS SANTOS",
        "boleto_url": "https://api.1pay.it/api/boleto/display/5e4294d6-7655-4ba6-99c5-748e5805c8a2",
        "due_date": "2025-04-23T03:00:00.000Z"
    },
    {
        "contact_id": "680a45b99296c3efe60ff1d4",
        "phone": "553588479377",
        "name": "RUBENS JOSE COTRIM",
        "boleto_url": "https://api.1pay.it/api/boleto/display/e88bfca6-90ae-423f-b24d-66917ab71270",
        "due_date": "2025-04-23T03:00:00.000Z"
    },
    {
        "contact_id": "680a45bfd636ac0d8709fa76",
        "phone": "553599133695",
        "name": "PATRICIA PASSOS FERREIRA",
        "boleto_url": "https://api.1pay.it/api/boleto/display/8db2ac2e-18c3-42bb-bd59-1599ee5e579e",
        "due_date": "2025-04-24T03:00:00.000Z"
    },
    {
        "contact_id": "680a45c58ded7b11e40beb16",
        "phone": "553597003588",
        "name": "GISELE GOMES PEREIRA",
        "boleto_url": "https://api.1pay.it/api/boleto/display/5a5b0e89-613b-40e1-8641-5e59a04c6afe",
        "due_date": "2025-04-24T03:00:00.000Z"
    }
]