[
    {
        "PayerName": "RICARDO DE PAULA GOMES",
        "ExternalStatus": "PENDING",
        "BoletoUrl": "https://api.1pay.it/api/boleto/display/61922f96-1939-487b-ab04-52a74ece963e",
        "PayerPhone": "553588225673",
        "DueDate": "2025-03-15T03:00:00.000Z",
        "DaysDue": 20,
        "BoletoDigitalLine": "40192024098500000000110000825173710210000015000"
    },
    {
        "PayerName": "CLAUDIA TEODORA GOMES CODIGNOLE",
        "ExternalStatus": "PENDING",
        "BoletoUrl": "https://api.1pay.it/api/boleto/display/01a14e34-7536-4f4b-8a29-227100bda246",
        "PayerPhone": "553588119245",
        "DueDate": "2025-03-15T03:00:00.000Z",
        "DaysDue": 20,
        "BoletoDigitalLine": "40192025081600000000600000947531610210000015000"
    },
    {
        "PayerName": "ANDREZA APARECIDA DA SILVA",
        "ExternalStatus": "PENDING",
        "BoletoUrl": "https://api.1pay.it/api/boleto/display/53419023-8acd-4c36-a22a-454049e21226",
        "PayerPhone": "553597170749",
        "DueDate": "2025-03-18T03:00:00.000Z",
        "DaysDue": 17,
        "BoletoDigitalLine": "40192024254200000000200000715177410240000015000"
    },
    {
        "PayerName": "ROSA NEIDE PEREIRA",
        "ExternalStatus": "PENDING",
        "BoletoUrl": "https://api.1pay.it/api/boleto/display/f3ba9187-7beb-4b92-a363-00e10106bf66",
        "PayerPhone": "553598772067",
        "DueDate": "2025-03-20T03:00:00.000Z",
        "DaysDue": 15,
        "BoletoDigitalLine": "40192025083600000000400002683712910260000100000"
    },
    {
        "PayerName": "TANIA MARA DE OLIVEIRA FERREIRA",
        "ExternalStatus": "PENDING",
        "BoletoUrl": "https://api.1pay.it/api/boleto/display/e6dfb3f1-8a9e-4a5d-9333-2cb00604af06",
        "PayerPhone": "553588093511",
        "DueDate": "2025-03-20T03:00:00.000Z",
        "DaysDue": 15,
        "BoletoDigitalLine": "40192024334500000000500002420412910260000015000"
    },
    {
        "PayerName": "FERNANDO LEITE",
        "ExternalStatus": "PENDING",
        "BoletoUrl": "https://api.1pay.it/api/boleto/display/6093a969-5d8a-4de7-8cce-ff16b11e7fe8",
        "PayerPhone": "553592395876",
        "DueDate": "2025-03-20T03:00:00.000Z",
        "DaysDue": 15,
        "BoletoDigitalLine": "40192024335200000000100001737568110260000047150"
    },
    {
        "PayerName": "KARINA MEIRE DA SILVA",
        "ExternalStatus": "PENDING",
        "BoletoUrl": "https://api.1pay.it/api/boleto/display/0a6fff46-399b-4304-be18-11ea1d26a1e2",
        "PayerPhone": "553599921447",
        "DueDate": "2025-03-20T03:00:00.000Z",
        "DaysDue": 15,
        "BoletoDigitalLine": "40192024257700000000800002060036410260000015000"
    },
    {
        "PayerName": "Beatriz Ribeiro dos Santos",
        "ExternalStatus": "PENDING",
        "BoletoUrl": "https://api.1pay.it/api/boleto/display/5e74ac3f-6f60-4ac6-a821-0529bd2d433e",
        "PayerPhone": "553588325336",
        "DueDate": "2025-03-20T03:00:00.000Z",
        "DaysDue": 15,
        "BoletoDigitalLine": "40192025083800000000000000684639810260000016000"
    },
    {
        "PayerName": "RITA ELEOTERIO DE SIQUEIRA",
        "ExternalStatus": "PENDING",
        "BoletoUrl": "https://api.1pay.it/api/boleto/display/efc8023c-800c-422b-9f0c-76a16cdd4377",
        "PayerPhone": "553588086200",
        "DueDate": "2025-03-20T03:00:00.000Z",
        "DaysDue": 15,
        "BoletoDigitalLine": "40192025081500000000800006057368810260000023000"
    },
    {
        "PayerName": "ALEXANDRE RABELO DE CARVALHO",
        "ExternalStatus": "PENDING",
        "BoletoUrl": "https://api.1pay.it/api/boleto/display/3705e6f5-c865-473f-8645-f85dea2d2db4",
        "PayerPhone": "553598727702",
        "DueDate": "2025-03-20T03:00:00.000Z",
        "DaysDue": 15,
        "BoletoDigitalLine": "40192023188100000000000003336609610260000038696"
    },
    {
        "PayerName": "JESSICA NOELI DA SILVA FERNANDES",
        "ExternalStatus": "PENDING",
        "BoletoUrl": "https://api.1pay.it/api/boleto/display/4ae11651-1c96-4949-80e8-ddaad86604aa",
        "PayerPhone": "553588653156",
        "DueDate": "2025-03-20T03:00:00.000Z",
        "DaysDue": 15,
        "BoletoDigitalLine": "40192024335200000000100002145340710260000028366"
    },
    {
        "PayerName": "GERALDA AURELIO DOS SANTOS",
        "ExternalStatus": null,
        "BoletoUrl": null,
        "PayerPhone": null,
        "DueDate": "2025-03-20T03:00:00.000Z",
        "DaysDue": 15,
        "BoletoDigitalLine": null
    },
    {
        "PayerName": "GABRIEL MARQUES SILVA SOUZA",
        "ExternalStatus": "PENDING",
        "BoletoUrl": "https://api.1pay.it/api/boleto/display/9f8d5f37-91d4-4f61-a93a-edb56ea73f02",
        "PayerPhone": "553597573118",
        "DueDate": "2025-03-20T03:00:00.000Z",
        "DaysDue": 15,
        "BoletoDigitalLine": "40192024179500000000000000482992710260000015000"
    },
    {
        "PayerName": "ROZANA MARIA MACIEL FADINI",
        "ExternalStatus": "PENDING",
        "BoletoUrl": "https://api.1pay.it/api/boleto/display/01581aca-229d-4ddf-8a5c-be8632cbcd5c",
        "PayerPhone": "553592771333",
        "DueDate": "2025-03-20T03:00:00.000Z",
        "DaysDue": 15,
        "BoletoDigitalLine": "40192024252800000000100001481191210260000122350"
    },
    {
        "PayerName": "MARIA APARECIDA GOMES DE ALMEIDA(VANESSA)",
        "ExternalStatus": "PENDING",
        "BoletoUrl": "https://api.1pay.it/api/boleto/display/3dfea5da-48b7-471b-bb80-00b0081f5494",
        "PayerPhone": "553588314737",
        "DueDate": "2025-03-20T12:38:13.000Z",
        "DaysDue": 15,
        "BoletoDigitalLine": "40192025082000000000800005630009910260000016000"
    },
    {
        "PayerName": "JOSE VITOR DE AGUIAR",
        "ExternalStatus": "PENDING",
        "BoletoUrl": "https://api.1pay.it/api/boleto/display/ef27f65f-5e20-476c-ad02-444347d7502a",
        "PayerPhone": "553574008706",
        "DueDate": "2025-03-20T20:43:06.000Z",
        "DaysDue": 15,
        "BoletoDigitalLine": "40192025085100000000300002468072110260000012113"
    }
]